setup.py
trash_cli.py
trashcangourmand.egg-info/PKG-INFO
trashcangourmand.egg-info/SOURCES.txt
trashcangourmand.egg-info/dependency_links.txt
trashcangourmand.egg-info/entry_points.txt
trashcangourmand.egg-info/requires.txt
trashcangourmand.egg-info/top_level.txt