Metadata-Version: 1.2
Name: trashcangourmand
Version: 1.2.0
Summary: A scheduler to email you your own code to read
Home-page: https://github.com/howonlee/trashcan-gourmand
Author: Howon Lee
License: MIT
Project-URL: Documentation, https://github.com/howonlee/trashcan-gourmand
Project-URL: Source, https://github.com/howonlee/trashcan-gourmand
Project-URL: Tracker, https://github.com/howonlee/trashcan-gourmand/issues
Platform: UNKNOWN
Classifier: Development Status :: 3 - Alpha
Classifier: Environment :: Console
Classifier: Intended Audience :: Other Audience
Classifier: License :: OSI Approved :: MIT License
Classifier: Operating System :: POSIX
Requires-Python: >3.7
